{
    "emojis_details": [
        {
            "nombre": "ejemplo",
            "emoji": "feliz",
            "M1": "255",
            "M2": "255",
            "M3": "255",
            "M4": "255",
            "M5": "255",
            "M6": "255",
            "M7": "255",
            "M8": "255",
            "M9": "255",
            "M10": "255",
            "M11": "255",
            "M12": "255",
            "M13": "255",
            "M14": "255",
            "M15": "255",
            "M16": "255",
            "M17": "255",
            "M18": "255",
            "M19": "255"
        },
        {
            "nombre": "Otro Ejemplo",
            "emoji": "feliz",
            "M1": "0",
            "M2": "0",
            "M3": "0",
            "M4": "0",
            "M5": "0",
            "M6": "0",
            "M7": "0",
            "M8": "0",
            "M9": "0",
            "M10": "0",
            "M11": "0",
            "M12": "0",
            "M13": "0",
            "M14": "0",
            "M15": "0",
            "M16": "0",
            "M17": "0",
            "M18": "0",
            "M19": "0"
        }
    ]
}